adc_logger/__init__.py
adc_logger/configs.py
adc_logger/formatters.py
adc_logger/main.py
adc_logger/py.typed
adc_logger-0.1.0.dist-info/METADATA
adc_logger-0.1.0.dist-info/WHEEL
adc_logger-0.1.0.dist-info/top_level.txt
adc_logger-0.1.0.dist-info/RECORD
